README.md
setup.py
ArconSDK/ArconSDK.py
ArconSDK/__init__.py
ArconSDK.egg-info/PKG-INFO
ArconSDK.egg-info/SOURCES.txt
ArconSDK.egg-info/dependency_links.txt
ArconSDK.egg-info/entry_points.txt
ArconSDK.egg-info/requires.txt
ArconSDK.egg-info/top_level.txt