Metadata-Version: 2.1
Name: ArconSDK
Version: 0.1.1
Summary: ArconSDK: A Python package to get PWD 
Author: Anand Vishwakarma
Author-email: anand.v@arconnet.com
License: MIT
Requires-Dist: ipaddress
Requires-Dist: psutil
Requires-Dist: requests
Requires-Dist: pycryptodome
